mlquantify/__init__.py
mlquantify/base.py
mlquantify/base_aggregative.py
mlquantify/calibration.py
mlquantify/confidence.py
mlquantify/multiclass.py
mlquantify/adjust_counting/__init__.py
mlquantify/adjust_counting/_adjustment.py
mlquantify/adjust_counting/_base.py
mlquantify/adjust_counting/_counting.py
mlquantify/adjust_counting/_utils.py
mlquantify/likelihood/__init__.py
mlquantify/likelihood/_base.py
mlquantify/likelihood/_classes.py
mlquantify/meta/__init__.py
mlquantify/meta/_classes.py
mlquantify/metrics/__init__.py
mlquantify/metrics/_oq.py
mlquantify/metrics/_rq.py
mlquantify/metrics/_slq.py
mlquantify/mixture/__init__.py
mlquantify/mixture/_base.py
mlquantify/mixture/_classes.py
mlquantify/mixture/_utils.py
mlquantify/model_selection/__init__.py
mlquantify/model_selection/_protocol.py
mlquantify/model_selection/_search.py
mlquantify/model_selection/_split.py
mlquantify/neighbors/__init__.py
mlquantify/neighbors/_base.py
mlquantify/neighbors/_classes.py
mlquantify/neighbors/_classification.py
mlquantify/neighbors/_kde.py
mlquantify/neighbors/_utils.py
mlquantify/neural/__init__.py
mlquantify/utils/__init__.py
mlquantify/utils/_artificial.py
mlquantify/utils/_constraints.py
mlquantify/utils/_context.py
mlquantify/utils/_decorators.py
mlquantify/utils/_exceptions.py
mlquantify/utils/_get_scores.py
mlquantify/utils/_load.py
mlquantify/utils/_parallel.py
mlquantify/utils/_random.py
mlquantify/utils/_sampling.py
mlquantify/utils/_tags.py
mlquantify/utils/_validation.py
mlquantify/utils/prevalence.py
mlquantify-0.1.20.dist-info/METADATA
mlquantify-0.1.20.dist-info/WHEEL
mlquantify-0.1.20.dist-info/top_level.txt
mlquantify-0.1.20.dist-info/RECORD
