Metadata-Version: 2.4
Name: mlquantify
Version: 0.1.20
Summary: Quantification Library
Home-page: https://github.com/luizfernandolj/QuantifyML/tree/master
Maintainer: Luiz Fernando Luth Junior
Keywords: python,machine learning,quantification,quantify
Classifier: Development Status :: 4 - Beta
Classifier: Intended Audience :: Science/Research
Classifier: Programming Language :: Python :: 3
Classifier: Operating System :: Unix
Classifier: Operating System :: MacOS :: MacOS X
Classifier: Operating System :: Microsoft :: Windows
Requires-Dist: scikit-learn
Requires-Dist: numpy
Requires-Dist: scipy
Requires-Dist: joblib
Requires-Dist: tqdm
Requires-Dist: pandas
Requires-Dist: xlrd
Requires-Dist: matplotlib
Requires-Dist: abstention
Dynamic: classifier
Dynamic: description
Dynamic: description-content-type
Dynamic: home-page
Dynamic: keywords
Dynamic: maintainer
Dynamic: requires-dist
Dynamic: summary
